timerizer/__init__.py
timerizer/core.py
timerizer/tests/__init__.py
timerizer/tests/test_core.py
timerizer-0.1.1.dist-info/LICENSE
timerizer-0.1.1.dist-info/METADATA
timerizer-0.1.1.dist-info/WHEEL
timerizer-0.1.1.dist-info/top_level.txt
timerizer-0.1.1.dist-info/RECORD
