Metadata-Version: 2.1
Name: timerizer
Version: 0.1.1
Summary: A simple decorator to time function execution
Home-page: https://github.com/msaligs/timerizer
Author: msaligs
Author-email: msaligs@gmail.com
License: UNKNOWN
Project-URL: Bug Tracker, https://github.com/msaligs/timerizer/issues
Platform: UNKNOWN
Classifier: Programming Language :: Python :: 3
Classifier: License :: OSI Approved :: MIT License
Classifier: Operating System :: OS Independent
Requires-Python: >=3.6
License-File: LICENSE
